infinitecampusapi/InfiniteCampus.py
infinitecampusapi/__init__.py
infinitecampusapi/classes/AcademicSessions.py
infinitecampusapi/classes/Classes.py
infinitecampusapi/classes/Courses.py
infinitecampusapi/classes/Demographics.py
infinitecampusapi/classes/Enrollments.py
infinitecampusapi/classes/GradingPeriods.py
infinitecampusapi/classes/Orgs.py
infinitecampusapi/classes/Schools.py
infinitecampusapi/classes/Student.py
infinitecampusapi/classes/Students.py
infinitecampusapi/classes/Teachers.py
infinitecampusapi/classes/Terms.py
infinitecampusapi/classes/Users.py
infinitecampusapi/classes/__init__.py
infinitecampusapi/classes/auth.py
infinitecampusapi/classes/extras.py
infinitecampusapi-0.1.1.dist-info/LICENSE
infinitecampusapi-0.1.1.dist-info/METADATA
infinitecampusapi-0.1.1.dist-info/WHEEL
infinitecampusapi-0.1.1.dist-info/RECORD
