Metadata-Version: 2.3
Name: infinitecampusapi
Version: 0.1.1
Summary: A Python Wrapper for use with the Infinite Campus API
License: GNUGPLv3
Author: Alex Snyder
Author-email: 28544457+TheFuzzyTech@users.noreply.github.com
Requires-Python: >=3.13
Classifier: License :: Other/Proprietary License
Classifier: Programming Language :: Python :: 3
Classifier: Programming Language :: Python :: 3.13
Requires-Dist: pydantic[email] (>=2.11.1,<3.0.0)
Requires-Dist: requests (>=2.32.3,<3.0.0)
